<?xml version="1.0" ?>
<spellcast xmlns:xi="http://www.w3.org/2001/XInclude">
	<config
		RestingSet="$DayOrNightIdle"
		NormalSet="Idle"
		EngagedSet="$DayOrNight$MeleeSet"
		RequireVersion="2.22"
		ShowGearSwaps="false"
		Debug="True"
		FishingSet="GoFish"
		/>
	<sets>
		<group default = "true" name = "Standard">
			<set name = "DayIdle|Idle" BaseSet = "$DayOrNight$MeleeSet">
				<body>Iga Ningi +2</body>
				<hands>Iga Tekko +2</hands>
				<feet>Danzo Sune-ate</feet>
			</set>
			<set name = "NightIdle" BaseSet = "Idle">
				<feet>Ninja Kyahan</feet>
			</set>
			<set name = "DayTP|TP">
				<sub />
				<ammo>Qirmiz Tathlum</ammo>
				<head>Iga Zukin +2</head>
				<neck>Iga Erimaki</neck>
				<lear>Suppanomimi</lear>
				<rear>Brutal Earring</rear>
				<body>Ninja Chainmail</body>
				<hands>Dusk Gloves</hands>
				<lring>Rajas Ring</lring>
				<rring>Keen Ring</rring>
				<back>Atheling Mantle</back>
				<waist>Twilight Belt</waist>
				<legs>Iga Hakama +2</legs>
				<feet>Iga Kyahan +2</feet>
			</set>
			<set name = "NightTP" BaseSet = "DayTP">
				<hands>Koga Tekko</hands>
			</set>
			<set name = "DayEva|Eva">
				<range>Ungur Boomerang</range>
				<head>Optical Hat</head>
				<neck>Evasion Torque</neck>
				<lear>Velocity Earring</lear>
				<rear>Dodge Earring</rear>
				<body>Aurore Doublet</body>
				<hands>Iga Tekko +2</hands>
				<lring>Rajas Ring</lring>
				<rring>Heed Ring</rring>
				<back>Boxer's Mantle</back>
				<waist>Sveltesse Gouriz</waist>
				<legs>Iga Hakama +2</legs>
				<feet>Ballerines</feet>
			</set>
			<set name = "NightEva" BaseSet = "DayEva">
				<legs>Koga Hakama</legs>
			</set>
			<set name = "DayAcc|NightAcc|Acc" BaseSet = "TP">
				<head>Optical Hat</head>
				<neck>Iga Erimaki</neck>
				<body>Iga Ningi +2</body>
				<lring>Lava's Ring</lring>
				<rring>Kusha's Ring</rring>
				<waist>Virtuoso Belt</waist>
			</set>
			<set name = "DayTank|Tank" BaseSet = "TP">
				<range>Ungur Boomerang</range>
				<ammo></ammo>
				<rring>Heed Ring</rring>
				<back>Boxer's Mantle</back>
				<feet>Ballerines</feet>
			</set>
			<set name = "NightTank" BaseSet = "Tank">
				<hands>Koga Tekko</hands>
			</set>
			<set name = "Enmity" BaseSet = "$DayOrNight$MeleeSet">
				<neck>Invidia Torque</neck>
				<rear>Eris' Earring</rear>
				<lring>Odium Ring</lring>
				<waist>Warwolf Belt</waist>
			</set>
			<set name = "DayPDT|NightPDT|PDT" BaseSet = "$DayOrNightEva">
				<head>Arhat's Jinpachi +1</head>
				<neck>Twilight Torque</neck>
				<body>Arhat's Gi +1</body>
				<hands>Seiryu's Kote</hands>
				<lring>Jelly Ring</lring>
				<rring>Dark Ring</rring>
			</set>
			<set name = "DayParry|NightParry|Parry" BaseSet = "PDT">
				<head>Brisk Mask</head>
				<neck>Twilight Torque</neck>
				<lear>Beetle Earring +1</lear>
				<rear>Beetle Earring +1</rear>
				<body>Haubergeon</body>
				<hands>Seiryu's Kote</hands>
				<lring>Jelly Ring</lring>
				<rring>Dark Ring</rring>
				<back>Boxer's Mantle</back>
				<waist>Warwolf Belt</waist>
				<legs>Ambusher's Hose</legs>
				<feet>Ninja Kyahan</feet>
			</set>
			<set name = "Ninjutsu">
				<head>Ninja Hatsuburi</head>
				<!-- for MAcc until Torque -->
				<neck>Artemis' Medal</neck>
				<hands>Koga Tekko</hands>
				<!--<feet>Koga Kyahan</feet>-->
			</set>
			<set name = "EleNin" BaseSet="Ninjutsu">
				<!--<range></range>-->
				<ammo>Snow Sachet</ammo>
				<!--<head>Koga Hatsuburi</head>-->
				<neck>Artemis' Medal</neck>
				<lear>Moldavite Earring</lear>
				<rear>Hecate's Earring</rear>
				<!--<body></body>-->
				<hands>Iga Tekko +2</hands>
				<lring>Diamond Ring</lring>
				<rring>Spiral Ring</rring>
				<!--<back></back>
				<waist></waist>
				<legs></legs>-->
				<!--<feet>Ninja Kyahan +1</feet>-->
			</set>
			<set name = "WS" BaseSet = "$DayOrNight$MeleeSet">
				<head>Iga Zukin +2</head>
				<neck>Iga Erimaki</neck>
				<lear>Coral Earring</lear>
				<rear>Brutal Earring</rear>
				<body>Iga Ningi +2</body>
				<hands>Iga Tekko +2</hands>
				<lring>Rajas Ring</lring>
				<rring>Airy Ring</rring>
				<!--<rring>Spiral Ring</rring>-->
				<back>Iga Dochugappa</back>
				<!--<waist>Virtuoso Belt</waist>-->
				<waist>Warwolf Belt</waist>
				<legs>Iga Hakama +2</legs>
				<feet>Iga Kyahan +2</feet>
			</set>
			<set name = "Rest" />
			<set name = "Town" BaseSet = "$DayOrNightIdle" />
			<set name = "DayHaste|Haste" BaseSet = "$DayOrNight$MeleeSet">
				<head>Iga Zukin +2</head>
				<!--Only affects Cast Time, not Recast Time.  -->
				<body>Mirke Wardecors</body>
				<hands>Dusk Gloves</hands>
				<waist>Twilight Belt</waist>
				<legs>Iga Hakama +2</legs>
				<feet>Iga Kyahan +2</feet>
			</set>
			<set name = "NightHaste" BaseSet = "Haste">
				<hands>Koga Tekko</hands>
			</set>
			<set name = "RAcc" BaseSet = "$DayOrNight$MeleeSet">
				<head>Optical Hat</head>
				<body>Koga Chainmail</body>
				<hands>Seiryu's Kote</hands>
			</set>
			<set name = "Gun" BaseSet = "RAcc">
				<range>Coffinmaker</range>
				<ammo>Bullet</ammo>
			</set>
			<set name = "Dart" BaseSet = "RAcc">
				<ammo>Pinwheel</ammo>
			</set>
			<set name = "Boom" BaseSet = "RAcc">
				<range>Ungur Boomerang</range>
			</set>
			<set name = "GoFish">
				<head>Trainee's Spectacles</head>
				<body>Fisherman's tunica</body>
				<hands>Fisherman's gloves</hands>
				<legs>Angler's Hose</legs>
				<feet>Fisherman's Boots</feet>
			</set>
		</group>
		<!-- Campaign Battle gear - only used when Allied Tags are on -->
		<group name = "Camp" inherit = "Standard">
			<set name = "WS" BaseSet = "TP">
				<head>Optical Hat</head>
				<neck>Bull Necklace</neck>
				<lear>Coral Earring</lear>
				<rear>Brutal Earring</rear>
				<body>Haubergeon</body>
				<hands>Iga Tekko +2</hands>
				<lring>Rajas Ring</lring>
				<rring>Airy Ring</rring>
				<back />
				<waist>Warwolf Belt</waist>
				<legs>Byakko's Haidate</legs>
				<feet>Iga Kyahan +2</feet>
			</set>
		</group>
		<group name = "Siege" inherit = "Standard" />
		<group name = "Assault" inherit = "Standard" />
		<group name = "Abyssea" inherit = "Standard">
			<set name = "DayTP|TP">
				<sub />
				<ammo>Qirmiz Tathlum</ammo>
				<head>Iga Zukin +2</head>
				<neck>Iga Erimaki</neck>
				<lear>Suppanomimi</lear>
				<rear>Brutal Earring</rear>
				<body>Ninja Chainmail</body>
				<hands>Dusk Gloves</hands>
				<lring>Lava's Ring</lring>
				<rring>Kusha's Ring</rring>
				<back>Atheling Mantle</back>
				<waist>Twilight Belt</waist>
				<legs>Iga Hakama +2</legs>
				<feet>Iga Kyahan +2</feet>
			</set>
			<set name = "WS" BaseSet = "$DayOrNight$MeleeSet">
				<head>Iga Zukin +2</head>
				<neck>Iga Erimaki</neck>
				<lear>Coral Earring</lear>
				<rear>Brutal Earring</rear>
				<body>Iga Ningi +2</body>
				<hands>Iga Tekko +2</hands>
				<lring>Lava's Ring</lring>
				<rring>Kusha's Ring</rring>
				<!--<rring>Spiral Ring</rring>-->
				<back>Iga Dochugappa</back>back>
				<!--<waist>Virtuoso Belt</waist>-->
				<waist>Warwolf Belt</waist>
				<legs>Iga Hakama +2</legs>
				<feet>Iga Kyahan +2</feet>
			</set>
		</group>
		<group name = "Dynamis" inherit = "Standard" />
	</sets>
	<variables>
		<!-- Engaged Melee Gear -->
		<var name="MeleeSet">TP</var>
		<!-- Ranged Weapon Type -->
		<var name="RType">Dart</var>
		<!-- Init with day set will update after first cast/ja etc.-->
		<var name="DayOrNight">Day</var>
		<var name="BattleArea">Standard</var>
		<!-- Obi Rules -->
		<var name = "ThunderObi">1</var>
		<var name = "IceObi">1</var>
	</variables>
	<rules>
		<!-- Check there's nothing stopping us acting -->
		<xi:include href = "/includes/inc.xml" xpointer = "/includes/include[@name='ReturnRules']/*" />
		<!-- Equip town gears :) -->
		<xi:include href="/includes/inc.xml" xpointer="/includes/include[@name='IdleSettings']/*" />
		<!-- Check to see if we are in a battlefield type thing -->
		<xi:include href="/includes/inc.xml" xpointer="/includes/include[@name='BattleArea']/*" />
		<!-- Timecheck -->
		<xi:include href="/includes/inc.xml" xpointer="/includes/include[@name='TimeCheck']/*" />
		<!-- auto cancel sneak/utsu/stoneskin/blink when recasting them. Requires Cancel Plugin-->
		<xi:include href="/includes/inc.xml" xpointer="/includes/include[@name='CancelRules']/*" />
		<!-- Check to see what Moon Phase we are in -->
		<xi:include href = "/includes/moon.xml" xpointer = "/includes/include[@name='Moon']/*" />
		<!-- Default melee gears engaged -->
		<equip when = "engaged" setgroup = "$BattleArea" set = "$DayOrNight$MeleeSet" />
		<!-- Aftercast rules -->
		<if NotStatus="engaged">
			<equip when = "aftercast" setgroup = "$BattleArea" set = "$DayOrNightIdle" />
		</if>
		<else>
			<equip when = "aftercast" setgroup = "$BattleArea" set = "$DayOrNight$MeleeSet" />
		</else>
		<!-- lock ranged weapons when we have TP-->
		<if TPGT="9">
			<if advanced='"$MeleeSet" == "Eva" OR "$MeleeSet" == "Tank"'>
				<equip when="precast|midcast|aftercast">
					<ammo lock="t" />
				</equip>
			</if>
			<else>
				<equip when="precast|midcast|aftercast">
					<range lock="t" />
				</equip>
			</else>
		</if>
		<!-- Lock items that affect abilities -->
		<if BuffActive="Migawari">
			<equip when = "engaged" setgroup = "$BattleArea" set = "$DayOrNight$MeleeSet">
				<body lock="true">Iga Ningi +2</body>
			</equip>
			<action type = "command">input /echo Migawari</action>
		</if>
		<if BuffActive="March">
			<equip when = "engaged" setgroup = "$BattleArea" set = "$DayOrNight$MeleeSet">
				<body lock="true">Iga Ningi +2</body>
			</equip>
			<action type = "command">input /echo March</action>
		</if>
		<!-- rules for job abilities and actions -->
		<if Spell = "Blade:*">
			<if Spell = "*Chi|*Jin|*Kamu">
				<equip when = "precast" setgroup = "$BattleArea" set = "WS">
					<neck>Thunder Gorget</neck>
					<waist>Thunder Belt</waist>
					<legs>Byakko's Haidate</legs>
				</equip>
				<if Spell = "*Kamu" advanced='"$DayOrNight" == "Night"'>
					<equip when = "precast">
						<hands>Koga Tekko</hands>
					</equip>
				</if>
				<castdelay delay = "0.2" />
				<aftercastdelay delay = "4" />
			</if>
			<elseif Spell = "*Ku|*Ten">
				<equip when = "precast" setgroup = "$BattleArea" set = "WS">
					<neck>Soil Gorget</neck>
					<waist>Soil Belt</waist>
					<legs>Byakko's Haidate</legs>
				</equip>
				<castdelay delay = "0.2" />
				<aftercastdelay delay = "4" />
			</elseif>
			<else>
				<equip when = "precast" setgroup = "$BattleArea" set = "WS" />
				<aftercastdelay delay = "4" />
			</else>
		</if>
		<if Spell ="Cataclysm|Aeolian Edge">
				<equip when = "precast" setgroup = "$BattleArea" set = "WS|EleNin">
					<if advanced = '$MoonPhase &gt; 2'>
						<neck lock = "yes">Artemis' Medal</neck>
					</if>
				</equip>
				<aftercastdelay delay = "2" />
		</if>
		<!-- some DNC sub rules -->
		<if Spell="Curing Waltz II" TPGT="49">
			<changespell Spell="Curing Waltz III" />
		</if>
		<if Spell = "*Step">
			<equip when = "precast" setgroup = "$BattleArea" set = "Acc" />
			<aftercastdelay delay = "1" />
		</if>
		<!-- Job Abilities -->
		<if Spell = "Provoke|Animated Flourish|Warcry|Berserk|Yonin">
			<equip when = "precast" setgroup = "$BattleArea" set = "Enmity" />
			<aftercastdelay delay = "1" />
		</if>
		<if Spell = "Futae">
			<equip when = "precast">
				<hands>Iga Tekko +2</hands>
			</equip>
		</if>
		<!-- Ninjutsu Rules -->
		<if Spell = "Kurayami*|Dokumori*|Hojo*|Jubaku*|Aisha*|Yurin*">
			<equip when = "precast" setgroup = "$BattleArea" set = "Enmity|Ninjutsu">
				<rear>Loquac. Earring</rear>
				<body>Mirke Wardecors</body>
			</equip>
		</if>
		<if Spell = "Doton*|Suiton*|Huton*|Katon*|Hyoton*|Raiton*">
			<equip when = "precast" setgroup = "$BattleArea" set = "EleNin" />
			<!-- Handle Elemental Obi's -->
			<xi:include href = "/includes/inc.xml" xpointer = "/includes/include[@name='ObiRules']/*" />
		</if>
		<if spell="Utsusemi*|Migawari*|Myoshu*">
			<if HPPLT="26">
				<equip when = "precast" setgroup = "$BattleArea" set = "$DayOrNightEva">
					<!--just need two pieces for haste cap-->
					<ammo lock="yes"></ammo>
					<head>Iga Zukin +2</head>
					<lear>Shinobi Earring</lear>
					<rear>Loquac. Earring</rear>
					<body>Mirke Wardecors</body>
					<feet>Iga Kyahan +2</feet>
				</equip>
			</if>
			<else>
				<equip when = "precast" setgroup = "$BattleArea" set = "Enmity|$DayOrNightHaste" />
			</else>
			<if spell="Utsusemi*">
				<equip when = "precast">
					<neck>Magoraga Beads</neck>
					<rear>Loquac. Earring</rear>
				</equip>
				<if spell="Utsusemi: Ichi" BuffActive="Copy Image">
					<midcastdelay delay="3.0" />
					<command when = "midcast">cancel 66</command>
				</if>
			</if>
			<aftercastdelay delay = "1" />
		</if>
		<if Spell = "Tonko*|Monomi*">
			<equip when = "precast" setgroup = "$BattleArea" set = "Ninjutsu">
				<rear>Loquac. Earring</rear>
				<body>Mirke Wardecors</body>
			</equip>
		</if>
		<if Spell = "Ranged">
			<action type = "command">input /echo $RType</action>
			<equip when = "precast" setgroup = "$BattleArea" set = "$RType" />
			<!-- wait until we actually have a ranged weapon equiped -->
			<castdelay delay = "0.2" />
			<aftercastdelay delay = "2" />
		</if>
	</rules>
</spellcast>
<!-- vim: set ts=4 ff=unix : -->
